imgtools_m8/__init__.py
imgtools_m8/exceptions.py
imgtools_m8/helper.py
imgtools_m8/img_expander.py
imgtools_m8/img_tools.py
imgtools_m8/model_conf.py
imgtools_m8/model_scale_selector.py
imgtools_m8/multiprocess.py
imgtools_m8/process_conf.py
imgtools_m8/models/EDSR_x2.pb
imgtools_m8/models/EDSR_x3.pb
imgtools_m8/models/EDSR_x4.pb
tests/__init__.py
tests/helper.py
tests/test_helper.py
tests/test_img_expander.py
tests/test_img_tools.py
tests/test_model_conf.py
tests/test_model_scale_selector.py
tests/test_multiprocess.py
tests/test_precess_conf.py
tests/sources_test/a.txt
tests/sources_test/b.txt
tests/sources_test/bad_image.jpg
tests/sources_test/mar.jpg
tests/sources_test/recien_llegado.jpg
tests/sources_test/recien_llegado_min.jpg
imgtools_m8-1.1.0.dist-info/LICENCE
imgtools_m8-1.1.0.dist-info/METADATA
imgtools_m8-1.1.0.dist-info/WHEEL
imgtools_m8-1.1.0.dist-info/top_level.txt
imgtools_m8-1.1.0.dist-info/RECORD
