Metadata-Version: 2.1
Name: imgtools-m8
Version: 1.1.0
Summary: Simple image tools package. Used to convert, downscale or upscale images.
Home-page: https://github.com/mano8/imgtools_m8
Author: Eli Serra
Author-email: eli.serra173@gmail.com
License: Apache
Classifier: License :: OSI Approved :: Apache Software License
Classifier: Programming Language :: Python :: 3
Classifier: Programming Language :: Python :: 3.5
Classifier: Programming Language :: Python :: 3.6
Classifier: Programming Language :: Python :: 3.7
Classifier: Programming Language :: Python :: 3.8
Classifier: Programming Language :: Python :: 3.9
Classifier: Programming Language :: Python :: 3.10
Requires-Python: >3.5.2
License-File: LICENCE
Requires-Dist: opencv-contrib-python >=4.7.0.72
Requires-Dist: ve-utils >=2.5.3
Requires-Dist: numpy >=1.25.0
Provides-Extra: test
Requires-Dist: pytest >=7.1.2 ; extra == 'test'
Requires-Dist: coverage ; extra == 'test'
